evpython/__init__.py
evpython/main.py
evpython-0.1.2.dist-info/WHEEL
evpython-0.1.2.dist-info/METADATA
evpython-0.1.2.dist-info/RECORD
