Metadata-Version: 2.1
Name: evpython
Version: 0.1.2
Summary: 
Keywords: Environment Variables,Encryption,Sharing
Author: Henrique Cunha
Requires-Python: >=3.10,<4.0
Classifier: Programming Language :: Python :: 3
Classifier: Programming Language :: Python :: 3.10
Requires-Dist: pycryptodome (>=3.14.1,<4.0.0)
